<?xml version = "1.0" encoding = "UTF-8"?>

<beans xmlns="http://www.springframework.org/schema/beans"
	xmlns:xsi="http://www.w3.org/2001/XMLSchema-instance"
	xsi:schemaLocation="http://www.springframework.org/schema/beans
   http://www.springframework.org/schema/beans/spring-beans-3.0.xsd">
	<bean id="dynamicCommandController"
		class="shortcutHelper.backend.dynamicCommand.DynamicCommandController">
		<property name="shortcutRegistrationHelper" ref="ShortcutRegistrationHelper"></property>
		<property name="dynamicCommands" ref="dynamicCommands"></property>
		<property name="dynamicCommandObservers" ref="dynamicCommandObservers"></property>
	</bean>
</beans>
